python_percentage/__init__.py
python_percentage-1.0.0.dist-info/LICENSE.txt
python_percentage-1.0.0.dist-info/METADATA
python_percentage-1.0.0.dist-info/WHEEL
python_percentage-1.0.0.dist-info/top_level.txt
python_percentage-1.0.0.dist-info/RECORD
