Metadata-Version: 2.1
Name: python-percentage
Version: 1.0.0
Summary: Calculate percentages without worrying about ZeroDivision errors
Home-page: https://github.com/rogervila/python_percentage
Author: Roger Vilà
Author-email: rogervila@me.com
License: MIT
Download-URL: https://github.com/rogervila/python_percentage/archive/1.0.0.tar.gz
Keywords: calculate percentages,python percentage,float percentage,zerodivision,zero division
Platform: UNKNOWN
Classifier: Development Status :: 5 - Production/Stable
Classifier: Intended Audience :: Developers
Classifier: Topic :: Software Development :: Build Tools
Classifier: License :: OSI Approved :: MIT License
Classifier: Programming Language :: Python :: 3.9
License-File: LICENSE.txt
